jupyter_server_fileid/__init__.py
jupyter_server_fileid/cli.py
jupyter_server_fileid/extension.py
jupyter_server_fileid/handler.py
jupyter_server_fileid/manager.py
jupyter_server_fileid/pytest_plugin.py
jupyter_server_fileid-0.9.1.data/data/etc/jupyter/jupyter_server_config.d/jupyter_server_fileid.json
jupyter_server_fileid-0.9.1.dist-info/METADATA
jupyter_server_fileid-0.9.1.dist-info/WHEEL
jupyter_server_fileid-0.9.1.dist-info/entry_points.txt
jupyter_server_fileid-0.9.1.dist-info/licenses/LICENSE
jupyter_server_fileid-0.9.1.dist-info/RECORD
